data_doctor/__init__.py
data_doctor/__version__.py
data_doctor/cleaner.py
data_doctor/io.py
data_doctor/pipeline.py
data_doctor/transformer.py
data_doctor/validator.py
data_doctor_lib-0.1.0.dist-info/licenses/LICENSE
data_doctor_lib-0.1.0.dist-info/METADATA
data_doctor_lib-0.1.0.dist-info/WHEEL
data_doctor_lib-0.1.0.dist-info/top_level.txt
data_doctor_lib-0.1.0.dist-info/RECORD
