Metadata-Version: 2.4
Name: data_doctor_lib
Version: 0.1.0
Summary: A Python library for cleaning and preprocessing pandas DataFrames with an optional PyQt GUI
Author: Noah Harshbarger
Author-email: Noah Harshbarger <noahharshb@gmail.com>
License: MIT
Requires-Python: >=3.9
License-File: LICENSE
Requires-Dist: pandas>=2.0.0
Requires-Dist: numpy>=1.25.0
Requires-Dist: scikit-learn>=1.3.0
Requires-Dist: PyQt5>=5.15.9
Provides-Extra: dev
Requires-Dist: pytest>=7.4.0; extra == "dev"
Requires-Dist: black>=23.7.0; extra == "dev"
Requires-Dist: flake8>=6.1.0; extra == "dev"
Dynamic: license-file
